tkdragfiles.py
tkdragfiles-0.0.1.dist-info/LICENSE
tkdragfiles-0.0.1.dist-info/METADATA
tkdragfiles-0.0.1.dist-info/WHEEL
tkdragfiles-0.0.1.dist-info/top_level.txt
tkdragfiles-0.0.1.dist-info/RECORD
