Metadata-Version: 2.1
Name: tkdragfiles
Version: 0.0.1
Summary: Easy Drag Files and Drop to Tkinter
Author-email: nicehero <85948597@qq.com>
Project-URL: Homepage, https://github.com/nicehero/tkdragfiles
Project-URL: Issues, https://github.com/nicehero/tkdragfiles/issues
Classifier: Programming Language :: Python :: 3
Classifier: License :: OSI Approved :: Apache Software License
Classifier: Operating System :: OS Independent
Requires-Python: >=3.5
License-File: LICENSE
